src/__init__.py
src/gather.py
src/gogather.py
gogather-0.1.7.dist-info/LICENSE
gogather-0.1.7.dist-info/METADATA
gogather-0.1.7.dist-info/WHEEL
gogather-0.1.7.dist-info/entry_points.txt
gogather-0.1.7.dist-info/top_level.txt
gogather-0.1.7.dist-info/RECORD
