Metadata-Version: 2.1
Name: gogather
Version: 0.1.7
Summary: GatherDB - Go Gather
Home-page: https://github.com/rantlabs/rant
Author: Rajiv Gupta
Author-email: rgupta@gene.com
License: MIT
Keywords: Fast Configuration Management and State Database
Classifier: Programming Language :: Python :: 3
Classifier: License :: OSI Approved :: MIT License
Classifier: Operating System :: OS Independent
Requires-Python: >=3.6
License-File: LICENSE
Requires-Dist: netmiko
Requires-Dist: atpbar
